requests_mock/__init__.py
requests_mock/__init__.pyi
requests_mock/adapter.py
requests_mock/adapter.pyi
requests_mock/exceptions.py
requests_mock/exceptions.pyi
requests_mock/mocker.py
requests_mock/mocker.pyi
requests_mock/py.typed
requests_mock/request.py
requests_mock/request.pyi
requests_mock/response.py
requests_mock/response.pyi
requests_mock/contrib/__init__.py
requests_mock/contrib/_pytest_plugin.py
requests_mock/contrib/_pytest_plugin.pyi
requests_mock/contrib/fixture.py
requests_mock-1.12.0.dist-info/LICENSE
requests_mock-1.12.0.dist-info/METADATA
requests_mock-1.12.0.dist-info/WHEEL
requests_mock-1.12.0.dist-info/entry_points.txt
requests_mock-1.12.0.dist-info/top_level.txt
requests_mock-1.12.0.dist-info/RECORD
