Metadata-Version: 2.1
Name: requests-mock
Version: 1.12.0
Summary: Mock out responses from the requests package
Home-page: https://requests-mock.readthedocs.io/
Author: Jamie Lennox
Author-email: jamielennox@gmail.com
License: Apache-2
Project-URL: Source, https://github.com/jamielennox/requests-mock
Classifier: Development Status :: 5 - Production/Stable
Classifier: Intended Audience :: Developers
Classifier: Intended Audience :: Information Technology
Classifier: License :: OSI Approved :: Apache Software License
Classifier: Operating System :: OS Independent
Classifier: Programming Language :: Python
Classifier: Programming Language :: Python :: 3
Classifier: Programming Language :: Python :: 3.8
Classifier: Programming Language :: Python :: 3.9
Classifier: Programming Language :: Python :: 3.10
Classifier: Programming Language :: Python :: 3.11
Classifier: Programming Language :: Python :: 3.12
Classifier: Programming Language :: Python :: Implementation :: CPython
Classifier: Programming Language :: Python :: Implementation :: PyPy
Classifier: Topic :: Software Development :: Testing
License-File: LICENSE
Requires-Dist: requests<3,>=2.22
Provides-Extra: fixture
Requires-Dist: fixtures; extra == "fixture"
